{"openapi":"3.0.1","info":{"title":"OpenAPI definition","version":"v0"},"servers":[{"url":"http://localhost:8080","description":"Generated server url"}],"paths":{"/book/update":{"post":{"tags":["book-crud-controller"],"operationId":"update","requestBody":{"content":{"application/json":{"schema":{"$ref":"#/components/schemas/UpdateBookRequest"}}},"required":true},"responses":{"200":{"description":"OK","content":{"*/*":{"schema":{"$ref":"#/components/schemas/BookInfo"}}}}}}},"/book/read":{"post":{"tags":["book-crud-controller"],"operationId":"read","requestBody":{"content":{"application/json":{"schema":{"$ref":"#/components/schemas/ReadBookRequest"}}},"required":true},"responses":{"200":{"description":"OK","content":{"*/*":{"schema":{"$ref":"#/components/schemas/BookInfo"}}}}}}},"/book/delete":{"post":{"tags":["book-crud-controller"],"operationId":"delete","requestBody":{"content":{"application/json":{"schema":{"$ref":"#/components/schemas/DeleteBookRequest"}}},"required":true},"responses":{"200":{"description":"OK"}}}},"/book/create":{"post":{"tags":["book-crud-controller"],"operationId":"create","requestBody":{"content":{"application/json":{"schema":{"$ref":"#/components/schemas/CreateBookRequest"}}},"required":true},"responses":{"200":{"description":"OK","content":{"*/*":{"schema":{"$ref":"#/components/schemas/BookInfo"}}}}}}}},"components":{"schemas":{"UpdateBookRequest":{"type":"object","properties":{"bookId":{"type":"integer","format":"int64"},"bookName":{"type":"string"},"isbn":{"type":"string"}}},"BookInfo":{"type":"object","properties":{"bookId":{"type":"integer","format":"int64"},"bookName":{"type":"string"},"isbn":{"type":"string"},"createAt":{"type":"string","format":"date-time"},"updateAt":{"type":"string","format":"date-time"}}},"ReadBookRequest":{"type":"object","properties":{"bookId":{"type":"integer","format":"int64"}}},"DeleteBookRequest":{"type":"object","properties":{"bookId":{"type":"integer","format":"int64"}}},"CreateBookRequest":{"type":"object","properties":{"bookName":{"type":"string"},"isbn":{"type":"string"}}}}}}